setup.py
Resound.egg-info/PKG-INFO
Resound.egg-info/SOURCES.txt
Resound.egg-info/dependency_links.txt
Resound.egg-info/requires.txt
Resound.egg-info/top_level.txt
resound/__init__.py
resound/resound.py