Metadata-Version: 1.0
Name: Resound
Version: 1.2
Summary: Audio clip fingerprinting library
Home-page: https://github.com/cgearhart/Resound
Author: Chris Gearhart
Author-email: chris@gearley.com
License: CC0
Keywords: audio,fingerprinting
Platform: UNKNOWN
